snake_gym_grid/__init__.py
snake_gym_grid/wrappers.py
snake_gym_grid/envs/__init__.py
snake_gym_grid/envs/controller.py
snake_gym_grid/envs/snake_gym_grid.py
snake_gym_grid/envs/view.py
snake_gym_grid-0.5.0.dist-info/LICENSE
snake_gym_grid-0.5.0.dist-info/METADATA
snake_gym_grid-0.5.0.dist-info/WHEEL
snake_gym_grid-0.5.0.dist-info/top_level.txt
snake_gym_grid-0.5.0.dist-info/RECORD
