Metadata-Version: 2.1
Name: snake-gym-grid
Version: 0.5.0
Summary: An implementation on Snake game with grid display
License-File: LICENSE
Requires-Dist: gym (>=0.21.0)
Requires-Dist: pygame (==2.1.2)
Requires-Dist: numpy (>=1.12.0)
Requires-Dist: opencv-contrib-python (==4.5.5.64)
Requires-Dist: opencv-python (==4.5.5.64)
